spix.py
spix-1.5.0.data/data/share/man/man1/spix.1
spix-1.5.0.dist-info/AUTHORS
spix-1.5.0.dist-info/LICENSE.txt
spix-1.5.0.dist-info/METADATA
spix-1.5.0.dist-info/WHEEL
spix-1.5.0.dist-info/entry_points.txt
spix-1.5.0.dist-info/top_level.txt
spix-1.5.0.dist-info/zip-safe
spix-1.5.0.dist-info/RECORD
