Metadata-Version: 2.1
Name: spix
Version: 1.5.0
Summary: Yet another TeX compilation tool: simple, human readable, no option, no magic.
Home-page: http://framagit.org/spalax/spix
Author: Louis Paternault
Author-email: spalax@gresille.org
License: GPLv3 or any later version
Project-URL: Documentation, http://spix.readthedocs.io
Project-URL: Source, https://framagit.org/spalax/spix
Project-URL: Tracker, https://framagit.org/spalax/spix/issues
Keywords: tex latex compilation
Classifier: Development Status :: 5 - Production/Stable
Classifier: License :: OSI Approved :: GNU General Public License v3 or later (GPLv3+)
Classifier: Programming Language :: Python :: 3 :: Only
Classifier: Programming Language :: Python :: 3.8
Classifier: Programming Language :: Python :: 3.9
Classifier: Programming Language :: Python :: 3.10
Classifier: Programming Language :: Python :: 3.11
Classifier: Programming Language :: Python :: 3.12
Classifier: Programming Language :: Python :: 3.13
Classifier: Topic :: Text Processing :: Markup :: LaTeX
Requires-Python: <4,>=3.8
License-File: LICENSE.txt
License-File: AUTHORS
